src/__init__.py
src/api.py
src/cli.py
src/history.py
src/utils.py
smms.py-0.1.1.dist-info/LICENSE
smms.py-0.1.1.dist-info/METADATA
smms.py-0.1.1.dist-info/WHEEL
smms.py-0.1.1.dist-info/entry_points.txt
smms.py-0.1.1.dist-info/top_level.txt
smms.py-0.1.1.dist-info/RECORD
