Metadata-Version: 2.1
Name: smms.py
Version: 0.1.1
Summary: command line toolkit for managing images at https://sm.ms
Home-page: UNKNOWN
Author: Queensferry
Author-email: queensferry.me@gmail.com
License: MIT
Platform: UNKNOWN
Classifier: Programming Language :: Python :: 3
Classifier: License :: OSI Approved :: MIT License
Classifier: Operating System :: OS Independent
Requires-Dist: Click (>=7.0)
Requires-Dist: requests (>=2.20)
